beamas/__init__.py
beamas/beamas.py
beamas-1.0.0.dist-info/LICENSE.txt
beamas-1.0.0.dist-info/METADATA
beamas-1.0.0.dist-info/WHEEL
beamas-1.0.0.dist-info/top_level.txt
beamas-1.0.0.dist-info/RECORD
