Metadata-Version: 2.1
Name: beamas
Version: 1.0.0
Summary: Beam Analysis Software
Author-email: beamas <beamas.contact@gmail.com>
License: MIT
Requires-Python: >=3.6
License-File: LICENSE.txt
Requires-Dist: numpy
Requires-Dist: matplotlib
Requires-Dist: scipy
